{
    "arr_boxes": [
        {
            "x": 85.0145298242569,
            "y": 1303.9445268511772,
            "width": 133.27274322509766,
            "height": 43.322468280792236,
            "genre": "mujer",
            "class": "zapatos"
        },
        {
            "x": 314.9424719810486,
            "y": 885.8043757677078,
            "width": 63.72117519378662,
            "height": 117.77839756011963,
            "genre": "mujer",
            "class": "guantes y manopla"
        },
        {
            "x": 222.3256015777588,
            "y": 1221.2139475941658,
            "width": 83.23311924934387,
            "height": 108.76111161708832,
            "genre": "mujer",
            "class": "zapatos"
        },
        {
            "x": 180.8252513408661,
            "y": 645.81484156847,
            "width": 175.62143325805664,
            "height": 206.8890849351883,
            "genre": "mujer",
            "class": "camisas"
        },
        {
            "x": 140.2047836780548,
            "y": 1040.7306529283524,
            "width": 158.37300539016724,
            "height": 267.3635815382004,
            "genre": "mujer",
            "class": "pantalones"
        },
        {
            "x": 109.62807565927505,
            "y": 726.4430277347565,
            "width": 228.17222446203232,
            "height": 359.12222123146057,
            "genre": "mujer",
            "class": "bolso"
        }
    ],
    "file_name": "66vztft5kvvlr47jtpiewo5giivld10gf13pxj5jme199ij5kc1hlck7t3y2lub7.jpg"
}