{
    "arr_boxes": [
        {
            "x": 423.517541885376,
            "y": 636.9349908828735,
            "width": 280.89333057403564,
            "height": 81.3589096069336,
            "genre": "hombre",
            "class": "pantalones cortos"
        },
        {
            "x": 399.4674611091614,
            "y": 229.01747703552246,
            "width": 330.3090190887451,
            "height": 467.2532558441162,
            "genre": "hombre",
            "class": "chaquetas"
        }
    ],
    "file_name": "677fermdnazoohvigns8dpybqpd796mi3iy6lr0u9cqq65q8uzio1uaxyp137ok6.jpg"
}