{
    "arr_boxes": [
        {
            "x": 385.21427750587463,
            "y": 97.98826351761818,
            "width": 134.01567220687866,
            "height": 99.80332106351852,
            "genre": "mujer",
            "class": "gafas de sol"
        },
        {
            "x": 360.2158856391907,
            "y": 610.6625095009804,
            "width": 499.3257808685303,
            "height": 763.9934822916985,
            "genre": "mujer",
            "class": "pantalones"
        }
    ],
    "file_name": "7pgff7is41q1ku6emswqwcayif4g3v4mwz6nianhd0rmpew1gvaz6i4fgs0lzpg9.jpg"
}