{
    "arr_boxes": [
        {
            "x": 751.9406247138977,
            "y": 1090.210710644722,
            "width": 71.13913536071777,
            "height": 70.8029568195343,
            "genre": "mujer",
            "class": "zapatos"
        },
        {
            "x": 658.8273096084595,
            "y": 743.4443008899689,
            "width": 81.04202270507812,
            "height": 80.23814487457275,
            "genre": "mujer",
            "class": "bolso"
        },
        {
            "x": 690.6953001022339,
            "y": 622.9810492992401,
            "width": 124.99913692474365,
            "height": 202.53664922714233,
            "genre": "mujer",
            "class": "camisas"
        },
        {
            "x": 706.9592070579529,
            "y": 831.2912650108337,
            "width": 124.90837097167969,
            "height": 288.7591395378113,
            "genre": "mujer",
            "class": "pantalones"
        }
    ],
    "file_name": "87y3d36lzcogfdkbxo5zxsyqlpfmy2bcf5vb5l58mv9a6ru0p41i3h5e1a6adlh1.jpg"
}