{
    "arr_boxes": [
        {
            "x": 202.78563916683197,
            "y": 250.02110740542412,
            "width": 120.33545672893524,
            "height": 52.36709117889404,
            "genre": "mujer",
            "class": "gafas de sol"
        },
        {
            "x": 29.598117470741272,
            "y": 392.68181800842285,
            "width": 350.50935208797455,
            "height": 417.409307718277,
            "genre": "mujer",
            "class": "abrigos"
        }
    ],
    "file_name": "d36dfiffvqufnj7i09jvmlp2pgo56pug5hwoi3ht5eykn5z5ts4y6n6fd9liqexf.jpg"
}