{
    "arr_boxes": [
        {
            "x": 256.4732229709625,
            "y": 422.78331249952316,
            "width": 115.15506148338318,
            "height": 135.2920663356781,
            "genre": "mujer",
            "class": "zapatos"
        },
        {
            "x": 393.728569149971,
            "y": 54.87001433968544,
            "width": 126.55298233032227,
            "height": 126.73288285732269,
            "genre": "mujer",
            "class": "zapatos"
        }
    ],
    "file_name": "en93t4jki9w6qlgmqqcqiog0x3unw92764tnp2j04v3zqadxaoqqwnuk9d2zlfye.jpg"
}