{
    "arr_boxes": [
        {
            "x": 610.9289574623108,
            "y": 131.6514097005129,
            "width": 79.97368812561035,
            "height": 46.339113384485245,
            "genre": "mujer",
            "class": "gafas de sol"
        },
        {
            "x": 91.02222204208374,
            "y": 398.4308180809021,
            "width": 132.8523552417755,
            "height": 106.14211452007294,
            "genre": "mujer",
            "class": "zapatos"
        },
        {
            "x": 602.9593205451965,
            "y": 72.50825922936201,
            "width": 158.1164789199829,
            "height": 129.86503971368074,
            "genre": "mujer",
            "class": "sombreros"
        },
        {
            "x": 210.17759263515472,
            "y": 339.3851145207882,
            "width": 308.25216829776764,
            "height": 151.4732337296009,
            "genre": "mujer",
            "class": "pantalones"
        },
        {
            "x": 480.3368353843689,
            "y": 196.5924253463745,
            "width": 331.2205410003662,
            "height": 306.9304168820381,
            "genre": "mujer",
            "class": "camisas"
        }
    ],
    "file_name": "gd1c85b25et673nxhar2zydry3nwrm0xu53omdwxo7yzh3ls73yndnq3yjtaazbo.jpg"
}