{
    "arr_boxes": [
        {
            "x": 344.9165439605713,
            "y": 301.7331612110138,
            "width": 71.01167678833008,
            "height": 43.69614601135254,
            "genre": "hombre",
            "class": "gafas de sol"
        },
        {
            "x": 323.68075489997864,
            "y": 854.2714476585388,
            "width": 64.88632678985596,
            "height": 82.54719257354736,
            "genre": "hombre",
            "class": "zapatos"
        },
        {
            "x": 387.97420620918274,
            "y": 815.0990509986877,
            "width": 94.52623844146729,
            "height": 92.92103290557861,
            "genre": "hombre",
            "class": "zapatos"
        },
        {
            "x": 330.7596945762634,
            "y": 610.6801557540894,
            "width": 143.435697555542,
            "height": 250.32207012176514,
            "genre": "hombre",
            "class": "pantalones"
        },
        {
            "x": 269.1028171777725,
            "y": 321.8176066875458,
            "width": 315.4171746969223,
            "height": 381.64865612983704,
            "genre": "hombre",
            "class": "abrigos"
        }
    ],
    "file_name": "m5wby2poq2fexgj98ood6fy6k46r74q2toe7c118tfs76681ccv0qoo3o6imdqqx.jpg"
}