{
    "arr_boxes": [
        {
            "x": 329.142644405365,
            "y": 489.80475425720215,
            "width": 49.98899459838867,
            "height": 70.01492500305176,
            "genre": "mujer",
            "class": "pendientes"
        },
        {
            "x": 328.07533979415894,
            "y": 272.9450011253357,
            "width": 307.721107006073,
            "height": 175.8188009262085,
            "genre": "mujer",
            "class": "gafas de sol"
        },
        {
            "x": 239.98022317886353,
            "y": 688.3367371559143,
            "width": 303.2308316230774,
            "height": 391.9529414176941,
            "class": "collares"
        },
        {
            "x": 127.04951405525208,
            "y": 697.8385806083679,
            "width": 526.7512929439545,
            "height": 382.83089876174927,
            "genre": "mujer",
            "class": "camisas"
        },
        {
            "x": 564.9200820922852,
            "y": 355.41616916656494,
            "width": 508.3132839202881,
            "height": 702.5203657150269,
            "genre": "mujer",
            "class": "bolso"
        }
    ],
    "file_name": "pale561cep2zdiysrhpytz4e327nxhwl15almurxuukpmk4ggnvwsacvcop5gq40.jpg"
}