{
    "arr_boxes": [
        {
            "x": 564.5957708358765,
            "y": 647.2541436553001,
            "width": 89.14040565490723,
            "height": 82.79685527086258,
            "genre": "hombre",
            "class": "sombreros"
        },
        {
            "x": 78.04011583328247,
            "y": 743.1583911180496,
            "width": 124.1200590133667,
            "height": 128.62372398376465,
            "genre": "hombre",
            "class": "zapatos"
        },
        {
            "x": 417.26280212402344,
            "y": 1235.4367107152939,
            "width": 200.55136442184448,
            "height": 98.9894449710846,
            "genre": "hombre",
            "class": "zapatos"
        },
        {
            "x": 150.12173652648926,
            "y": 678.5222500562668,
            "width": 447.57792234420776,
            "height": 244.86964344978333,
            "genre": "hombre",
            "class": "camisas"
        },
        {
            "x": 170.73471665382385,
            "y": 698.3972579240799,
            "width": 410.3178870677948,
            "height": 583.1736624240875,
            "genre": "hombre",
            "class": "pantalones"
        }
    ],
    "file_name": "wamzdrrqj25sa4ozi1gn10botu2ozdoa2haaikjmg0to01l0swzyzq4zy1c25vh1.jpg"
}