{
    "arr_boxes": [
        {
            "x": 563.4664106369019,
            "y": 524.4546085596085,
            "width": 79.41570281982422,
            "height": 64.57553386688232,
            "genre": "hombre",
            "class": "relojes"
        },
        {
            "x": 796.4239239692688,
            "y": 673.2978808879852,
            "width": 101.52693271636963,
            "height": 78.22509169578552,
            "genre": "hombre",
            "class": "pulseras"
        },
        {
            "x": 328.48549246788025,
            "y": 91.88009910285473,
            "width": 186.5821623802185,
            "height": 146.65898121893406,
            "genre": "mujer",
            "class": "sombreros"
        },
        {
            "x": 298.3949375152588,
            "y": 287.1287503838539,
            "width": 261.5458273887634,
            "height": 211.9770035147667,
            "genre": "mujer",
            "class": "bufandas"
        },
        {
            "x": 244.41694021224976,
            "y": 585.2644658088684,
            "width": 579.674506187439,
            "height": 227.57969498634338,
            "genre": "mujer",
            "class": "pantalones"
        },
        {
            "x": 207.17106699943542,
            "y": 300.52242547273636,
            "width": 378.86207699775696,
            "height": 484.7408589720726,
            "genre": "mujer",
            "class": "chaquetas"
        },
        {
            "x": 548.3827829360962,
            "y": 226.11384898424149,
            "width": 430.15942096710205,
            "height": 466.3435658812523,
            "genre": "hombre",
            "class": "chaquetas"
        }
    ],
    "file_name": "wr2zzr880b1f3v6tazctiy1tv1lep0l1fdt26na113hl5jc8mv34zldwp12kxq6s.jpg"
}