{
    "arr_boxes": [
        {
            "x": 331.40477657318115,
            "y": 679.1570162773132,
            "width": 120.2062439918518,
            "height": 92.21022605895996,
            "genre": "hombre",
            "class": "sombreros"
        },
        {
            "x": 245.70058643817902,
            "y": 765.7165789604187,
            "width": 222.90349423885345,
            "height": 320.7947516441345,
            "genre": "hombre",
            "class": "abrigos"
        }
    ],
    "file_name": "xovb5bko7tjatfg2v996bt8kep1n5ugtp819jh7331r8i9ivsnhv9tlobebvgle8.jpg"
}